[{"line":1,"elements":[{"start_timestamp":"2022-02-24T15:19:18.127Z","line":4,"name":"Anasafya butun butonlar","description":"","id":"anasayfabutonlar;anasafya-butun-butonlar","type":"scenario","keyword":"Scenario","steps":[{"result":{"duration":4558000000,"status":"passed"},"line":6,"name":"kullanici anasayfaya gider","match":{"location":"stepdefinitions.TurkceAnaSayfa.kullaniciAnasayfayaGider()"},"keyword":"Given "},{"result":{"duration":246000000,"status":"passed"},"line":8,"name":"kullanici kurumsal giris tiklar","match":{"location":"stepdefinitions.AnaSayfaButonlar.kullaniciKurumsalGirisTiklar()"},"keyword":"And "},{"result":{"duration":313000000,"status":"passed"},"line":9,"name":"kurumsal giris test edilir","match":{"location":"stepdefinitions.AnaSayfaButonlar.kurumsalGirisTestEdilir()"},"keyword":"Then "},{"result":{"duration":52000000,"status":"passed"},"line":10,"name":"kullanici bireysel girisi tiklar","match":{"location":"stepdefinitions.TurkceAnaSayfa.kullaniciBireyselGirisiTiklar()"},"keyword":"And "},{"result":{"duration":194000000,"status":"passed"},"line":11,"name":"kullanici cep telefonunu girer","match":{"location":"stepdefinitions.TurkceAnaSayfa.kullaniciCepTelefonunuGirer()"},"keyword":"And "},{"result":{"duration":97000000,"status":"passed"},"line":12,"name":"kullanici sifre girer","match":{"location":"stepdefinitions.TurkceAnaSayfa.kullaniciSifreGirer()"},"keyword":"And "},{"result":{"duration":3078000000,"status":"passed"},"line":13,"name":"kullanici giris yap tiklar","match":{"location":"stepdefinitions.TurkceAnaSayfa.kullaniciGirisYapTiklar()"},"keyword":"And "},{"result":{"duration":5067000000,"status":"passed"},"line":14,"name":"kullanici otp kodu girer","match":{"location":"stepdefinitions.TurkceAnaSayfa.kullaniciOtpKoduGirer()"},"keyword":"And "},{"result":{"duration":28000000,"status":"passed"},"line":15,"name":"giris yap test edilir","match":{"location":"stepdefinitions.AnaSayfaButonlar.girisYapTestEdilir()"},"keyword":"And "},{"result":{"duration":488000000,"status":"passed"},"line":16,"name":"kullanici cikis yapar","match":{"location":"stepdefinitions.AnaSayfaButonlar.kullaniciCikisYapar()"},"keyword":"And "},{"result":{"duration":713000000,"status":"passed"},"line":17,"name":"kullanici uye ol tiklar","match":{"location":"stepdefinitions.AnaSayfaButonlar.kullaniciUyeOlTiklar()"},"keyword":"Then "},{"result":{"duration":51000000,"status":"passed"},"line":18,"name":"uye ol test edilir","match":{"location":"stepdefinitions.AnaSayfaButonlar.uyeOlTestEdilir()"},"keyword":"And "},{"result":{"duration":3241000000,"status":"passed"},"line":19,"name":"Kullanici anasayfaya geri doner","match":{"location":"stepdefinitions.AnaSayfaButonlar.kullaniciAnasayfayaGeriDoner()"},"keyword":"And "},{"result":{"duration":146000000,"status":"passed"},"line":20,"name":"kullanici sifremi unuttum tiklar","match":{"location":"stepdefinitions.AnaSayfaButonlar.kullaniciSifremiUnuttumTiklar()"},"keyword":"Then "},{"result":{"duration":30000000,"status":"passed"},"line":21,"name":"sifremi unuttum test edilir","match":{"location":"stepdefinitions.AnaSayfaButonlar.sifremiUnuttumTestEdilir()"},"keyword":"And "},{"result":{"duration":3189000000,"status":"passed"},"line":22,"name":"Kullanici anasayfaya geri doner","match":{"location":"stepdefinitions.AnaSayfaButonlar.kullaniciAnasayfayaGeriDoner()"},"keyword":"And "},{"result":{"duration":282000000,"status":"passed"},"line":23,"name":"kullanici sayfayi kapatir","match":{"location":"stepdefinitions.TurkceAnaSayfa.kullaniciSayfayiKapatir()"},"keyword":"Then "}],"tags":[{"name":"@TestB"}]}],"name":"anasayfabutonlar","description":"","id":"anasayfabutonlar","keyword":"Feature","uri":"file:src/test/resources/features/anasayfabutonlar.feature","tags":[]}]